saures_api_client/__init__.py
saures_api_client/client.py
saures_api_client/constants.py
saures_api_client/exceptions.py
saures_api_client/misc.py
saures_api_client/types.py
saures_api_client-0.1.2.dist-info/WHEEL
saures_api_client-0.1.2.dist-info/METADATA
saures_api_client-0.1.2.dist-info/RECORD
